{"markdown":{"yaml":{"draft":true},"containsRefs":false,"markdown":"\n\nI've gotten a lot of well-meaning advice about going out more (e.g, a postdoc abroad, etc.). Turns out, this simply wasn't feasible for me by and large.\n\nWith friends who had broader experiences, I had some first-order approximations of what I was missing out on.\n\nFor as long as I can remember, I turned to YouTube and podcasts to compensate: for an introvert, being a fly on the wall who didn't have to engage worked out perfectly!\n\nIf not actual intel, I felt I caught enough of the vibe of places I couldn't be, so I largely avoided FOMO.\n\nI've never been particularly comfortable on social media, and I can't remember how or when Twitter became an exception. \n\nSo color me amused by this FT column suggesting that the real reason to leave Twitter is that it's... too comfortable?\n\nhttps://twitter.com/JohnRentoul/status/1591355838299799555?s=20&t=nesxsAEMs_n4K9Se8XvjtQ\n\nIt has, indeed, been a comfortable hangout for me: and surprisingly so, considering the nastiness it's known for. \n\nI've taken my chances here and it's largely been very fun, and I daresay my time here has influenced the way I think about many things, for better or worse.\n\nThat said, I suppose I do have my own \"real reasons\" for planning to move on. It's just... not the comfort 😀\n\nhttps://twitter.com/neeldhara/status/1590210797220687872?s=20&t=r1RjVgIzZBGBAg9c1HwyYA"},"formats":{"html":{"execute":{"fig-width":7,"fig-height":5,"fig-format":"retina","fig-dpi":96,"df-print":"default","error":false,"eval":true,"cache":null,"freeze":true,"echo":true,"output":true,"warning":true,"include":true,"keep-md":false,"keep-ipynb":false,"ipynb":null,"enabled":null,"daemon":null,"daemon-restart":false,"debug":false,"ipynb-filters":[],"engine":"markdown"},"render":{"keep-tex":false,"keep-source":false,"keep-hidden":false,"prefer-html":false,"output-divs":true,"output-ext":"html","fig-align":"default","fig-pos":null,"fig-env":null,"code-fold":"none","code-overflow":"scroll","code-link":false,"code-line-numbers":false,"code-tools":false,"tbl-colwidths":"auto","merge-includes":true,"latex-auto-mk":true,"latex-auto-install":true,"latex-clean":true,"latex-max-runs":10,"latex-makeindex":"makeindex","latex-makeindex-opts":[],"latex-tlmgr-opts":[],"latex-input-paths":[],"latex-output-dir":null,"link-external-icon":false,"link-external-newwindow":false,"self-contained-math":false,"format-resources":[]},"pandoc":{"standalone":true,"wrap":"none","default-image-extension":"png","to":"html","css":["../../css/styles.css"],"toc":true,"html-math-method":"katex","include-after-body":["../../footer.html"],"filters":["abstract-section"],"output-file":"index.html"},"language":{},"metadata":{"lang":"en","fig-responsive":true,"quarto-version":"1.2.262","theme":["simplex","../../custom.scss"],"js":"../../scripts.js","smooth-scroll":true,"anchor-sections":true,"page-layout":"full","title-block-banner":true,"draft":true},"extensions":{"book":{"multiFile":true}}}}}